{
  "$schema": "http://json-schema.org/draft-04/schema#",
  "id": "http://mcsc.usmc.mil/mc2sa/tsoa/soi/observed-platform-system/2.0/#ObservedPlatformSystem",
  "title": "ObservedPlatformSystem",
  "type": "object",
  "description": "An observed platform system described by its properties.",
  "version": "0.4.1",
  "javaType": "ObservedPlatformSystem",
  "properties": {
    "PlatformSystem": {
      "id": "",
      "title": "",
      "type": "array",
      "description": "",
      "version": "0.2",
      "javaType": "",
      "items": {
        "$ref": "PlatformSystem.json"
      },
      "minItems": 1,
      "additionalItems": false
    }
  },
  "additionalProperties": false
}